build/lib/odahuflow/trainer/helpers/conda.py
build/lib/odahuflow/trainer/helpers/fs.py
build/lib/odahuflow/trainer/helpers/log.py
build/lib/odahuflow/trainer/helpers/mlflow_helper.py
build/lib/odahuflow/trainer/helpers/templates/__init__.py
build/lib/odahuflow/trainer/helpers/templates/entrypoint.py
build/lib/odahuflow/trainer/helpers/wrapper/__init__.py
build/lib/odahuflow/trainer/helpers/wrapper/entities.py
build/lib/odahuflow/trainer/helpers/wrapper/wrapper.py
build/lib/odahuflow/trainer/mlflow_full/runner.py
build/lib/odahuflow/trainer/mlflow_projects/runner.py
build/lib/tests/__init__.py
build/lib/tests/test_entrypoint.py
odahu_flow_mlflow_runner-1.6.1.data/data/README.md
odahuflow/trainer/helpers/conda.py
odahuflow/trainer/helpers/fs.py
odahuflow/trainer/helpers/log.py
odahuflow/trainer/helpers/mlflow_helper.py
odahuflow/trainer/helpers/templates/__init__.py
odahuflow/trainer/helpers/templates/entrypoint.py
odahuflow/trainer/helpers/wrapper/__init__.py
odahuflow/trainer/helpers/wrapper/entities.py
odahuflow/trainer/helpers/wrapper/wrapper.py
odahuflow/trainer/mlflow_full/runner.py
odahuflow/trainer/mlflow_projects/runner.py
tests/__init__.py
tests/test_entrypoint.py
odahu_flow_mlflow_runner-1.6.1.dist-info/METADATA
odahu_flow_mlflow_runner-1.6.1.dist-info/WHEEL
odahu_flow_mlflow_runner-1.6.1.dist-info/entry_points.txt
odahu_flow_mlflow_runner-1.6.1.dist-info/top_level.txt
odahu_flow_mlflow_runner-1.6.1.dist-info/RECORD
