Metadata-Version: 2.1
Name: odahu-flow-mlflow-runner
Version: 1.6.1
Summary: UNKNOWN
Home-page: UNKNOWN
Author: Vlad Tokarev, Vitalik Solodilov
Author-email: vlad.tokarev.94@gmail.com, mcdkr@yandex.ru
License: Apache v2
Keywords: mlflow odahu-flow
Platform: UNKNOWN
Classifier: Programming Language :: Python :: 3.6
Classifier: Programming Language :: Python :: 3.7
Requires-Python: >=3.6
Requires-Dist: odahu-flow-sdk (==1.5.0rc7)
Requires-Dist: odahu-flow-cli (==1.5.0rc7)
Requires-Dist: mlflow (>=1.13.0)
Requires-Dist: PyYAML (>=3.1.2)
Provides-Extra: testing
Requires-Dist: pytest (>=5.1.2) ; extra == 'testing'
Requires-Dist: pytest-mock (>=1.10.4) ; extra == 'testing'
Requires-Dist: pytest-cov (>=2.7.1) ; extra == 'testing'
Requires-Dist: pylint (>=2.3.0) ; extra == 'testing'
